MANIFEST.in
README.md
requirements.txt
setup.py
pigeon/__init__.py
pigeon/config.py
pigeon/exceptions.py
pigeon/rest/__init__.py
pigeon/rest/authenticator.py
pigeon/rest/historical_candles.py
pigeon/rest/intraday_candles.py
pigeon/websocket/__init__.py
pigeon/websocket/websocket_client.py
pigeon/websocket/websocket_default_functions.py
pigeonapi_python_client.egg-info/PKG-INFO
pigeonapi_python_client.egg-info/SOURCES.txt
pigeonapi_python_client.egg-info/dependency_links.txt
pigeonapi_python_client.egg-info/requires.txt
pigeonapi_python_client.egg-info/top_level.txt