Metadata-Version: 2.1
Name: pigeonapi-python-client
Version: 0.13
Summary: Python package containing several classes and data for extracting and manipulating market and trading data.
Home-page: https://github.com/BTG-Pactual-Solutions/pigeonapi-python-client
Author: PigeonAPI powered by BTG Pactual Solutions
License: UNKNOWN
Platform: UNKNOWN
Requires-Python: >=3.7
